gamebanking/__init__.py
gamebanking-1.1.1.dist-info/METADATA
gamebanking-1.1.1.dist-info/WHEEL
gamebanking-1.1.1.dist-info/top_level.txt
gamebanking-1.1.1.dist-info/RECORD
