Metadata-Version: 2.4
Name: gamebanking
Version: 1.1.1
Summary: gamebanking is a module that makes coding currency in games easier.
Home-page: https://www.youtube.com/@CorruptDragon24
Author: CorruptDragon24
Requires-Python: >=3.6
Dynamic: author
Dynamic: description
Dynamic: description-content-type
Dynamic: home-page
Dynamic: requires-python
Dynamic: summary
